README.md
setup.py
src/pytest_xlog/__init__.py
src/pytest_xlog/plugin.py
src/pytest_xlog.egg-info/PKG-INFO
src/pytest_xlog.egg-info/SOURCES.txt
src/pytest_xlog.egg-info/dependency_links.txt
src/pytest_xlog.egg-info/entry_points.txt
src/pytest_xlog.egg-info/requires.txt
src/pytest_xlog.egg-info/top_level.txt