Metadata-Version: 1.2
Name: pytest-xlog
Version: 0.1.5
Summary: Extended logging for test and decorators
Home-page: https://github.com/YADRO-KNS/pytest-xlog
Author: Sergey Kozlov
License: MIT
Keywords: pytest yaml decorator log
Platform: any
Classifier: Development Status :: 4 - Beta
Classifier: Framework :: Pytest
Classifier: Intended Audience :: Developers
Classifier: License :: OSI Approved :: MIT License
Classifier: Operating System :: OS Independent
Classifier: Programming Language :: Python :: 3.6
Classifier: Programming Language :: Python :: 3.7
Classifier: Programming Language :: Python :: 3.8
Classifier: Topic :: Software Development :: Testing
Requires-Python: >=3.6
